{
  "forge_marker": 1,
  "defaults": {
    "model": "tfcelementia:empty",
    "textures": {
      "texture": "tfcelementia:blocks/fruit_trees/bark/date",
      "particle": "tfcelementia:blocks/fruit_trees/bark/date"
    }
  },
  "variants": {
    "normal": [
      {}
    ],
    "facing": {
      "up": {
        "submodel": "tfcelementia:fruit_trees/branch_vertical"
      },
      "down": {
        "submodel": "tfcelementia:fruit_trees/branch_vertical"
      },
      "north": {
        "submodel": "tfcelementia:fruit_trees/branch_horizontal"
      },
      "east": {
        "submodel": "tfcelementia:fruit_trees/branch_horizontal",
        "y": 90
      },
      "south": {
        "submodel": "tfcelementia:fruit_trees/branch_horizontal",
        "y": 180
      },
      "west": {
        "submodel": "tfcelementia:fruit_trees/branch_horizontal",
        "y": 270
      }
    },
    "north": {
      "0": {},
      "1": {"submodel": "tfcelementia:fruit_trees/branch_vertical_connection"},
      "2": {"submodel": "tfcelementia:fruit_trees/branch_horizontal_connection"}
    },
    "east": {
      "0": {},
      "1": {"submodel": "tfcelementia:fruit_trees/branch_vertical_connection", "y": 90},
      "2": {"submodel": "tfcelementia:fruit_trees/branch_horizontal_connection", "y": 90}
    },
    "south": {
      "0": {},
      "1": {"submodel": "tfcelementia:fruit_trees/branch_vertical_connection", "y": 180},
      "2": {"submodel": "tfcelementia:fruit_trees/branch_horizontal_connection", "y": 180}
    },
    "west": {
      "0": {},
      "1": {"submodel": "tfcelementia:fruit_trees/branch_vertical_connection", "y": 270},
      "2": {"submodel": "tfcelementia:fruit_trees/branch_horizontal_connection", "y": 270}
    },
    "up": {
      "0": {},
      "1": {},
      "2": {"submodel": "tfcelementia:fruit_trees/branch_horizontal_connection", "x": 270}
    }
  }
}