{
  "__comment__": "This file was automatically created by mcresources",
  "feature": "tfc:caverns/webbed/plant/tall_fescue_grass_patch",
  "placement": [
    {
      "type": "tfc:climate",
      "min_forest": "old_growth",
      "fuzzy": true
    },
    {
      "type": "minecraft:count",
      "count": 50
    },
    {
      "type": "minecraft:height_range",
      "height": {
        "type": "minecraft:uniform",
        "min_inclusive": {
          "absolute": -120
        },
        "max_inclusive": {
          "absolute": 40
        }
      }
    },
    {
      "type": "minecraft:count",
      "count": 12
    },
    {
      "type": "minecraft:in_square"
    },
    {
      "type": "tfc:biome"
    }
  ]
}