{
  "forge_marker": 1,
  "defaults": {
    "model": "leaves",
    "textures": {
      "all": "tfcflorae:blocks/wood/fruit_tree/leaves/osage_orange"
    }
  },
  "variants": {
    "normal": [
      {}
    ],
    "inventory": {
      "model": "leaves",
      "transform": "forge:default-block"
    },
    "state": {
      "normal": {
        "model": "leaves"
      },
      "flowering": {
        "model": "leaves",
        "textures": {
          "all": "tfcflorae:blocks/wood/fruit_tree/leaves/osage_orange",
          "texture": "tfcflorae:blocks/wood/fruit_tree/flowers/osage_orange"
        },
        "submodel": "tfc:fruit_trees/leaves_overlay"
      },
      "fruit": {
        "model": "leaves",
        "textures": {
          "all": "tfcflorae:blocks/wood/fruit_tree/leaves/osage_orange",
          "texture": "tfcflorae:blocks/wood/fruit_tree/fruit/osage_orange"
        },
        "submodel": "tfc:fruit_trees/leaves_overlay"
      }
    }
  }
}