{
  "multipart": [
    {
      "when": {
        "down": "true"
      },
      "apply": {
        "model": "tfcflorae:coral/fan/fire/black"
      }
    },
    {
      "when": {
        "east": "true"
      },
      "apply": {
        "model": "tfcflorae:coral/fan/fire/side/black",
        "y": 270
      }
    },
    {
      "when": {
        "north": "true"
      },
      "apply": {
        "model": "tfcflorae:coral/fan/fire/side/black",
        "y": 180
      }
    },
    {
      "when": {
        "south": "true"
      },
      "apply": {
        "model": "tfcflorae:coral/fan/fire/side/black"
      }
    },
    {
      "when": {
        "up": "true"
      },
      "apply": {
        "model": "tfcflorae:coral/fan/fire/black",
        "x": 180
      }
    },
    {
      "when": {
        "west": "true"
      },
      "apply": {
        "model": "tfcflorae:coral/fan/fire/side/black",
        "y": 90
      }
    }
  ]
}