{
  "__comment__": "This file was automatically created by mcresources",
  "type": "tfc:random_tree",
  "config": {
    "structures": [
      "tfc:greenheart_large/1",
      "tfc:greenheart_large/2",
      "tfc:greenheart_large/3",
      "tfc:greenheart_large/4",
      "tfc:greenheart_large/5",
      "tfc:greenheart_large/6",
      "tfc:greenheart_large/7",
      "tfc:greenheart_large/8",
      "tfc:greenheart_large/9",
      "tfc:greenheart_large/10",
      "tfc:greenheart_large/11",
      "tfc:greenheart_large/12",
      "tfc:greenheart_large/13"
    ],
    "radius": 2,
    "placement": {
      "width": 2,
      "height": 9,
      "allow_submerged": true
    }
  }
}