{
  "__comment__": "This file was automatically created by mcresources",
  "type": "tfc:random_tree",
  "config": {
    "structures": [
      "tfc:kauri/1",
      "tfc:kauri/2",
      "tfc:kauri/3",
      "tfc:kauri/4",
      "tfc:kauri/5",
      "tfc:kauri/6",
      "tfc:kauri/7",
      "tfc:kauri/8",
      "tfc:kauri/9",
      "tfc:kauri/10",
      "tfc:kauri/11",
      "tfc:kauri/12",
      "tfc:kauri/13",
      "tfc:kauri/14",
      "tfc:kauri/15",
      "tfc:kauri/16",
      "tfc:kauri/17",
      "tfc:kauri/18",
      "tfc:kauri/19",
      "tfc:kauri/20",
      "tfc:kauri/21"
    ],
    "radius": 1,
    "placement": {
      "width": 1,
      "height": 5,
      "allow_submerged": true
    }
  }
}