{
  "__comment__": "This file was automatically created by mcresources",
  "type": "tfc:random_tree",
  "config": {
    "structures": [
      "tfcflorae:pink_ivory/1",
      "tfcflorae:pink_ivory/2",
      "tfcflorae:pink_ivory/3",
      "tfcflorae:pink_ivory/4",
      "tfcflorae:pink_ivory/5",
      "tfcflorae:pink_ivory/6",
      "tfcflorae:pink_ivory/7",
      "tfcflorae:pink_ivory/8",
      "tfcflorae:pink_ivory/9",
      "tfcflorae:pink_ivory/10",
      "tfcflorae:pink_ivory/11",
      "tfcflorae:pink_ivory/12",
      "tfcflorae:pink_ivory/13",
      "tfcflorae:pink_ivory/14",
      "tfcflorae:pink_ivory/15",
      "tfcflorae:pink_ivory/16",
      "tfcflorae:pink_ivory/17",
      "tfcflorae:pink_ivory/18",
      "tfcflorae:pink_ivory/19"
    ],
    "radius": 1,
    "placement": {
      "width": 1,
      "height": 3,
      "allow_submerged": false
    }
  }
}