{
  "__comment__": "This file was automatically created by mcresources",
  "multipart": [
    {
      "when": {
        "up": "true"
      },
      "apply": {
        "model": "tfcflorae:block/rocky_compact_dirt/humus/wall/post/blueschist"
      }
    },
    {
      "when": {
        "north": "low"
      },
      "apply": {
        "model": "tfcflorae:block/rocky_compact_dirt/humus/wall/side/blueschist",
        "uvlock": true
      }
    },
    {
      "when": {
        "east": "low"
      },
      "apply": {
        "model": "tfcflorae:block/rocky_compact_dirt/humus/wall/side/blueschist",
        "y": 90,
        "uvlock": true
      }
    },
    {
      "when": {
        "south": "low"
      },
      "apply": {
        "model": "tfcflorae:block/rocky_compact_dirt/humus/wall/side/blueschist",
        "y": 180,
        "uvlock": true
      }
    },
    {
      "when": {
        "west": "low"
      },
      "apply": {
        "model": "tfcflorae:block/rocky_compact_dirt/humus/wall/side/blueschist",
        "y": 270,
        "uvlock": true
      }
    },
    {
      "when": {
        "north": "tall"
      },
      "apply": {
        "model": "tfcflorae:block/rocky_compact_dirt/humus/wall/side/tall/blueschist",
        "uvlock": true
      }
    },
    {
      "when": {
        "east": "tall"
      },
      "apply": {
        "model": "tfcflorae:block/rocky_compact_dirt/humus/wall/side/tall/blueschist",
        "y": 90,
        "uvlock": true
      }
    },
    {
      "when": {
        "south": "tall"
      },
      "apply": {
        "model": "tfcflorae:block/rocky_compact_dirt/humus/wall/side/tall/blueschist",
        "y": 180,
        "uvlock": true
      }
    },
    {
      "when": {
        "west": "tall"
      },
      "apply": {
        "model": "tfcflorae:block/rocky_compact_dirt/humus/wall/side/tall/blueschist",
        "y": 270,
        "uvlock": true
      }
    }
  ]
}