{
  "__comment__": "This file was automatically created by mcresources",
  "multipart": [
    {
      "when": {
        "up": "true"
      },
      "apply": {
        "model": "tfcflorae:block/rockier_compact_dirt/silt/wall/post/sandstone"
      }
    },
    {
      "when": {
        "north": "low"
      },
      "apply": {
        "model": "tfcflorae:block/rockier_compact_dirt/silt/wall/side/sandstone",
        "uvlock": true
      }
    },
    {
      "when": {
        "east": "low"
      },
      "apply": {
        "model": "tfcflorae:block/rockier_compact_dirt/silt/wall/side/sandstone",
        "y": 90,
        "uvlock": true
      }
    },
    {
      "when": {
        "south": "low"
      },
      "apply": {
        "model": "tfcflorae:block/rockier_compact_dirt/silt/wall/side/sandstone",
        "y": 180,
        "uvlock": true
      }
    },
    {
      "when": {
        "west": "low"
      },
      "apply": {
        "model": "tfcflorae:block/rockier_compact_dirt/silt/wall/side/sandstone",
        "y": 270,
        "uvlock": true
      }
    },
    {
      "when": {
        "north": "tall"
      },
      "apply": {
        "model": "tfcflorae:block/rockier_compact_dirt/silt/wall/side/tall/sandstone",
        "uvlock": true
      }
    },
    {
      "when": {
        "east": "tall"
      },
      "apply": {
        "model": "tfcflorae:block/rockier_compact_dirt/silt/wall/side/tall/sandstone",
        "y": 90,
        "uvlock": true
      }
    },
    {
      "when": {
        "south": "tall"
      },
      "apply": {
        "model": "tfcflorae:block/rockier_compact_dirt/silt/wall/side/tall/sandstone",
        "y": 180,
        "uvlock": true
      }
    },
    {
      "when": {
        "west": "tall"
      },
      "apply": {
        "model": "tfcflorae:block/rockier_compact_dirt/silt/wall/side/tall/sandstone",
        "y": 270,
        "uvlock": true
      }
    }
  ]
}